pgist.py
pgist-0.4.3.dist-info/DESCRIPTION.rst
pgist-0.4.3.dist-info/METADATA
pgist-0.4.3.dist-info/RECORD
pgist-0.4.3.dist-info/WHEEL
pgist-0.4.3.dist-info/entry_points.txt
pgist-0.4.3.dist-info/metadata.json
pgist-0.4.3.dist-info/top_level.txt
