Metadata-Version: 2.0
Name: pgist
Version: 0.4.3
Summary: A Python command-line wrapper with github3.py library to access GitHub Gist
Home-page: https://github.com/douglarek/pgist
Author: Lingchao Xin
Author-email: douglarek@gmail.com
License: Apache License
Requires-Dist: click (>=0.2)
Requires-Dist: github3.py (>=0.7.1)
